README.md
setup.cfg
setup.py
irisreader/__init__.py
irisreader/config.py
irisreader/file_hub.py
irisreader/get_lines.py
irisreader/has_line.py
irisreader/instrument.py
irisreader/iris_data_cube.py
irisreader/obs_iterator.py
irisreader/observation.py
irisreader/raster_cube.py
irisreader/sji_cube.py
irisreader.egg-info/PKG-INFO
irisreader.egg-info/SOURCES.txt
irisreader.egg-info/dependency_links.txt
irisreader.egg-info/not-zip-safe
irisreader.egg-info/requires.txt
irisreader.egg-info/top_level.txt
irisreader/coalignment/__init__.py
irisreader/coalignment/goes_data.py
irisreader/coalignment/hek_data.py
irisreader/coalignment/iris_sji_raster.py
irisreader/data/IRIS_SJI_test.fits
irisreader/data/IRIS_raster_test1.fits
irisreader/data/IRIS_raster_test2.fits
irisreader/data/__init__.py
irisreader/data/mg2k_centroids.npz
irisreader/data/mg2k_centroids.py
irisreader/data/sample.py
irisreader/data/20140518_151415_3820607204/IRIS_SJI_test.fits
irisreader/data/20140518_151415_3820607204/IRIS_raster_test1.fits
irisreader/data/20140518_151415_3820607204/IRIS_raster_test2.fits
irisreader/preprocessing/__init__.py
irisreader/preprocessing/image_cropper.py
irisreader/preprocessing/image_cube_cropper.py
irisreader/preprocessing/spectrum_interpolator.py
irisreader/utils/__init__.py
irisreader/utils/animate.py
irisreader/utils/coordinates.py
irisreader/utils/date.py
irisreader/utils/dbtools.py
irisreader/utils/download.py
irisreader/utils/fits.py
irisreader/utils/get_mg2k_features.py
irisreader/utils/lazy_file_header_list.py
irisreader/utils/notebooks.py