Metadata-Version: 2.1
Name: irisreader
Version: 0.3.2
Summary: IRISreader is a Python library that allows for efficient browsing through IRIS satellite data in order to simplify machine learning applications
Home-page: https://www.github.com/i4Ds/IRISreader
Author: Cedric Huwyler
Author-email: cedric.huwyler@fhnw.ch
License: MIT
Download-URL: https://github.com/i4Ds/IRISreader/archive/v0.3.2.tar.gz
Platform: UNKNOWN
